pywer/__init__.py
pywer/metrics.py
tests/__init__.py
tests/test_metrics.py
pywer-0.1.1.dist-info/LICENSE
pywer-0.1.1.dist-info/METADATA
pywer-0.1.1.dist-info/WHEEL
pywer-0.1.1.dist-info/top_level.txt
pywer-0.1.1.dist-info/RECORD
