Metadata-Version: 2.1
Name: pywer
Version: 0.1.1
Summary: A simple Python package to calculate word error rate (WER).
Home-page: https://github.com/jumon/pywer
Author: jumon
Author-email: jumon.nozaki@gmail.com
License: UNKNOWN
Platform: UNKNOWN
Classifier: Development Status :: 2 - Pre-Alpha
Classifier: Programming Language :: Python :: 3
Classifier: License :: OSI Approved :: MIT License
Classifier: Operating System :: OS Independent
Classifier: Topic :: Multimedia :: Sound/Audio :: Speech
Requires-Python: >=3.6
Requires-Dist: editdistance
